autoth/__init__.py
autoth/core.py
autoth-0.0.1.dist-info/LICENSE.MIT
autoth-0.0.1.dist-info/METADATA
autoth-0.0.1.dist-info/WHEEL
autoth-0.0.1.dist-info/top_level.txt
autoth-0.0.1.dist-info/RECORD
