Metadata-Version: 2.1
Name: autoth
Version: 0.0.1
Summary: Automatic threshold optimization
Home-page: https://github.com/pypa/sampleproject
Author: Qiuqiang Kong
Author-email: qiuqiangkong@gmail.com
License: UNKNOWN
Platform: UNKNOWN
Classifier: Programming Language :: Python :: 3
Classifier: License :: OSI Approved :: MIT License
Classifier: Operating System :: OS Independent
Requires-Python: >=3.6
